[
  {
    "id": "psi-cib-oregon-construction-contractors",
    "title": "PSI Candidate Information Bulletin — Oregon Construction Contractors",
    "url": null,
    "tier": 1,
    "description": "Official PSI exam blueprint covering format, content areas, and passing criteria for the Oregon CCB exam."
  },
  {
    "id": "oregon-ccb-prelicense",
    "title": "Oregon CCB Pre-License Education Requirements",
    "url": null,
    "tier": 1,
    "description": "Official CCB page describing the 16-hour pre-license training requirement."
  },
  {
    "id": "ors-chapter-701",
    "title": "ORS Chapter 701 — Construction Contractors",
    "url": null,
    "tier": 1,
    "description": "Oregon Revised Statutes governing construction contractor licensing, bonds, and enforcement."
  }
]
